pygmo/_patch_problem.py
pygmo/_patch_r_policy.py
pygmo/_ipyparallel_utils.py
pygmo/_r_policy_test.py
pygmo/core.cpython-39-x86_64-linux-gnu.so
pygmo/_py_algorithms.py
pygmo/_bfe_test.py
pygmo/_version.py
pygmo/_patch_algorithm.py
pygmo/__init__.py
pygmo/_check_deps.py
pygmo/_patch_topology.py
pygmo/_s_policy_test.py
pygmo/_mp_utils.py
pygmo/_problem_test.py
pygmo/_patch_s_policy.py
pygmo/_patch_island.py
pygmo/_island_test.py
pygmo/_patch_bfe.py
pygmo/_algorithm_test.py
pygmo/test.py
pygmo/_py_problems.py
pygmo/_py_bfes.py
pygmo/_topology_test.py
pygmo/_py_islands.py
pygmo/plotting/__init__.py
pygmo.libs/libnlopt-ed026f9e.so.0.11.1
pygmo.libs/libgfortran-ce9df58f.so.5.0.0
pygmo.libs/libblas-fe34f726.so.3.8.0
pygmo.libs/libtbb-330f1dc8.so.12.7
pygmo.libs/libpagmo-fdf175e5.so.9.0
pygmo.libs/libipopt-8adcd530.so.3.14.10
pygmo.libs/liblapack-31d7d384.so.3.8.0
pygmo.libs/libquadmath-aa18d9dd.so.0.0.0
pygmo.libs/libcoinmumps-077828a7.so.3.0.4
pygmo.libs/libboost_serialization-1464d039.so.1.80.0
pygmo-2.19.5.dist-info/WHEEL
pygmo-2.19.5.dist-info/top_level.txt
pygmo-2.19.5.dist-info/RECORD
pygmo-2.19.5.dist-info/METADATA
