Metadata-Version: 2.1
Name: pygmo
Version: 2.19.5
Summary: Parallel optimisation for Python
Home-page: https://github.com/esa/pygmo2
Author: The pagmo development team
Author-email: pagmo@googlegroups.com
License: MPL-2.0
Keywords: science math physics optimization ai evolutionary-computing parallel-computing metaheuristics
Platform: Unix
Classifier: Development Status :: 5 - Production/Stable
Classifier: Operating System :: OS Independent
Classifier: Intended Audience :: Science/Research
Classifier: Topic :: Scientific/Engineering
Classifier: Topic :: Scientific/Engineering :: Mathematics
Classifier: Topic :: Scientific/Engineering :: Physics
Classifier: License :: OSI Approved :: Mozilla Public License 2.0 (MPL 2.0)
Classifier: Programming Language :: Python :: 3
Requires-Dist: numpy
Requires-Dist: cloudpickle
Requires-Dist: scipy
